flywheel/__init__.py
flywheel/api_client.py
flywheel/client.py
flywheel/configuration.py
flywheel/drone_login.py
flywheel/file_spec.py
flywheel/finder.py
flywheel/flywheel.py
flywheel/gear_context.py
flywheel/partial_reader.py
flywheel/rest.py
flywheel/util.py
flywheel/view_builder.py
flywheel/api/__init__.py
flywheel/api/acquisitions_api.py
flywheel/api/analyses_api.py
flywheel/api/audit_trail_api.py
flywheel/api/auth_api.py
flywheel/api/batch_api.py
flywheel/api/bulk_api.py
flywheel/api/change_log_api.py
flywheel/api/collections_api.py
flywheel/api/config_api.py
flywheel/api/container_tasks_api.py
flywheel/api/container_type_api.py
flywheel/api/containers_api.py
flywheel/api/custom_filters_api.py
flywheel/api/data_view_executions_api.py
flywheel/api/dataexplorer_api.py
flywheel/api/devices_api.py
flywheel/api/dimse_api.py
flywheel/api/download_api.py
flywheel/api/files_api.py
flywheel/api/form_responses_api.py
flywheel/api/gears_api.py
flywheel/api/groups_api.py
flywheel/api/jobs_api.py
flywheel/api/jupyterlab_servers_api.py
flywheel/api/modalities_api.py
flywheel/api/packfiles_api.py
flywheel/api/projects_api.py
flywheel/api/protocols_api.py
flywheel/api/reports_api.py
flywheel/api/resolve_api.py
flywheel/api/roles_api.py
flywheel/api/sessions_api.py
flywheel/api/site_api.py
flywheel/api/staffing_pools_api.py
flywheel/api/subjects_api.py
flywheel/api/tasks_api.py
flywheel/api/tree_api.py
flywheel/api/uids_api.py
flywheel/api/upload_api.py
flywheel/api/users_api.py
flywheel/api/views_api.py
flywheel/models/__init__.py
flywheel/models/access_level.py
flywheel/models/access_permission.py
flywheel/models/access_permission_output.py
flywheel/models/access_permission_update.py
flywheel/models/access_type.py
flywheel/models/accumulator.py
flywheel/models/acquisition.py
flywheel/models/acquisition_container_output.py
flywheel/models/acquisition_copy_input.py
flywheel/models/acquisition_input.py
flywheel/models/acquisition_list_output.py
flywheel_sdk-21.3.0.dist-info/METADATA
flywheel_sdk-21.3.0.dist-info/WHEEL
flywheel_sdk-21.3.0.dist-info/licenses/LICENSE.txt
flywheel_sdk-21.3.0.dist-info/RECORD
